{
  "interactionModel": {
    "languageModel": {
      "invocationName": "Braingain",
      "intents": [
        {
          "name": "AMAZON.CancelIntent",
          "samples": []
        },
        {
          "name": "AMAZON.HelpIntent",
          "samples": []
        },
        {
          "name": "AMAZON.StopIntent",
          "samples": []
        },
        {
          "name": "AnzahlDerSpielerSetzenIntent",
          "slots": [
            {
              "name": "numberOfPlayers",
              "type": Integer,
            }
          ],
          "samples": [
            " Wir sind {numberOfPlayers} Spieler",
            " Wir wollen mit {numberOfPlayers} spielen"
          ]
        },
        {
          "name": "UsernamenSpeichernIntent",
          "slots": [
          	{
          		"name": "username",
          		"type": String,
          	}
          ],
          "samples": [
            "Ich heiﬂe {username}",
            "Ich bin {username}",
            "{username}"
          ]
        },
        {
          "name": "KategorieEinstellenIntent",
          "slots": [
          	{
          		"name": "gewaehlteKategorie",
          		"type": "LIST_OF_CATEGORIES",
          	}
          ],
          "samples": [
            "Ich will in Kategorie {gewaehlteKategorie} spielen",
            "Wir spielen {gewaehlteKategorie}",
            "{gewaehlteKategorie}",
            "Wir wollen {gewaehlteKategorie} spielen",
            "Die Kategorie ist {gewaehlteKategorie}"
          ]
        },
        {
          "name": "AMAZON.PauseIntent",
          "samples": []
        },
        {
          "name": "AMAZON.ResumeIntent",
          "samples": []
        }
      ],
      "types": [
        {
          "name": "LIST_OF_CATEGORIES",
          "values": [
            {
              "name": {
                "value": "Logik"
              }
            },
            {
              "name": {
                "value": "Mathe"
              }
            },
            {
              "name": {
                "value": "Gedaechtnistraining"
              }
            },
            {
              "name": {
                "value": "Geographie"
              }
            }
          ]
        }
      ]
    }
  }
}